Metadata-Version: 2.1
Name: django-db-only
Version: 0.0.1
Summary: Django models as standalone app.
Home-page: http://github.com/abrorbekuz/django_db_only
Author: Abror Qodirov
Author-email: splayerme@gmail.com
License: UNKNOWN
Platform: UNKNOWN
Classifier: Programming Language :: Python
Classifier: License :: OSI Approved :: Python Software Foundation License
Classifier: Development Status :: 3 - Alpha
Classifier: Operating System :: OS Independent
Classifier: Framework :: Django
Classifier: Intended Audience :: Developers
Classifier: Topic :: Internet :: WWW/HTTP :: Dynamic Content
